analyzeMFT/__init__.py
analyzeMFT/cli.py
analyzeMFT/config.py
analyzeMFT/constants.py
analyzeMFT/file_writers.py
analyzeMFT/hash_processor.py
analyzeMFT/mft_analyzer.py
analyzeMFT/mft_record.py
analyzeMFT/sqlite_writer.py
analyzeMFT/test_generator.py
analyzeMFT/validators.py
analyzeMFT/windows_time.py
analyzeMFT/sql/attribute_types.sql
analyzeMFT/sql/file_record_flags.sql
analyzeMFT/sql/schema.sql
analyzemft-3.1.1.dist-info/licenses/LICENSE.txt
analyzemft-3.1.1.dist-info/METADATA
analyzemft-3.1.1.dist-info/WHEEL
analyzemft-3.1.1.dist-info/entry_points.txt
analyzemft-3.1.1.dist-info/top_level.txt
analyzemft-3.1.1.dist-info/RECORD
