Metadata-Version: 2.4
Name: analyzeMFT
Version: 3.1.1
Summary: Analyze the $MFT from a NTFS filesystem.
Home-page: http://github.com/rowingdude/analyzeMFT
Author: Benjamin Cance
Author-email: kc8bws@kc8bws.com
License: LICENSE.txt
Classifier: Development Status :: 3 - Alpha
Classifier: Intended Audience :: Developers
Classifier: License :: OSI Approved :: MIT License
Classifier: Operating System :: OS Independent
Classifier: Programming Language :: Python :: 3
Classifier: Programming Language :: Python :: 3.8
Classifier: Programming Language :: Python :: 3.9
Classifier: Programming Language :: Python :: 3.10
Classifier: Programming Language :: Python :: 3.11
Classifier: Programming Language :: Python :: 3.12
Classifier: Programming Language :: Python :: 3.13
Requires-Python: >=3.8
License-File: LICENSE.txt
Requires-Dist: pywin32; platform_system == "Windows"
Requires-Dist: openpyxl==3.1.5
Dynamic: author
Dynamic: author-email
Dynamic: classifier
Dynamic: description
Dynamic: description-content-type
Dynamic: home-page
Dynamic: license
Dynamic: license-file
Dynamic: requires-dist
Dynamic: requires-python
Dynamic: summary
